odoo10_addon_l10n_es_irnr-10.0.1.0.0-py2.7-nspkg.pth
odoo/addons/l10n_es_irnr/README.rst
odoo/addons/l10n_es_irnr/__init__.py
odoo/addons/l10n_es_irnr/__manifest__.py
odoo/addons/l10n_es_irnr/data/fiscal_position_taxes_irnr.xml
odoo/addons/l10n_es_irnr/data/fiscal_positions_irnr.xml
odoo/addons/l10n_es_irnr/data/taxes_irnr.xml
odoo/addons/l10n_es_irnr/static/description/icon.png
odoo10_addon_l10n_es_irnr-10.0.1.0.0.dist-info/DESCRIPTION.rst
odoo10_addon_l10n_es_irnr-10.0.1.0.0.dist-info/METADATA
odoo10_addon_l10n_es_irnr-10.0.1.0.0.dist-info/RECORD
odoo10_addon_l10n_es_irnr-10.0.1.0.0.dist-info/WHEEL
odoo10_addon_l10n_es_irnr-10.0.1.0.0.dist-info/metadata.json
odoo10_addon_l10n_es_irnr-10.0.1.0.0.dist-info/namespace_packages.txt
odoo10_addon_l10n_es_irnr-10.0.1.0.0.dist-info/top_level.txt
